janela/__init__.py
janela/_impl/__init__.py
janela/_impl/mac.py
janela/_impl/wmctrl_xdotool_xlib.py
janela/interfaces/__init__.py
janela/interfaces/interface.py
janela/interfaces/models.py
janela/logger.py
janela/playground/__init__.py
janela/playground/mosaic.py
janela/util/__init__.py
janela/util/cmd.py
janela-0.0.8.dist-info/LICENSE
janela-0.0.8.dist-info/METADATA
janela-0.0.8.dist-info/WHEEL
janela-0.0.8.dist-info/RECORD
