Metadata-Version: 2.1
Name: janela
Version: 0.0.8
Summary: A simple tool to automate window management
Author: Gustavo
Author-email: github.dxabr@aleeas.com
Requires-Python: >=3.8,<4.0
Classifier: Programming Language :: Python :: 3
Classifier: Programming Language :: Python :: 3.8
Classifier: Programming Language :: Python :: 3.9
Classifier: Programming Language :: Python :: 3.10
Classifier: Programming Language :: Python :: 3.11
Classifier: Programming Language :: Python :: 3.12
Requires-Dist: pyobjc (>=10.0,<11.0) ; sys_platform == "darwin"
Requires-Dist: pyobjc-framework-Quartz (>=10.0,<11.0) ; sys_platform == "darwin"
Requires-Dist: python-xlib (>=0.33,<0.34) ; sys_platform == "linux"
